fps_uvicorn/__init__.py
fps_uvicorn/cli.py
fps_uvicorn/config.py
fps_uvicorn-0.0.20.dist-info/METADATA
fps_uvicorn-0.0.20.dist-info/WHEEL
fps_uvicorn-0.0.20.dist-info/entry_points.txt
fps_uvicorn-0.0.20.dist-info/licenses/LICENSE
fps_uvicorn-0.0.20.dist-info/RECORD
